ptcookie/__init__.py
ptcookie/ptcookie.py
ptcookie-0.0.1.dist-info/LICENSE
ptcookie-0.0.1.dist-info/METADATA
ptcookie-0.0.1.dist-info/WHEEL
ptcookie-0.0.1.dist-info/entry_points.txt
ptcookie-0.0.1.dist-info/top_level.txt
ptcookie-0.0.1.dist-info/RECORD
