Metadata-Version: 2.1
Name: ptcookie
Version: 0.0.1
Summary: Cookie Analyser
Home-page: https://www.penterep.com/
Author: Penterep
Author-email: info@penterep.com
License: GPLv3+
Platform: UNKNOWN
Classifier: Programming Language :: Python :: 3.6
Classifier: Programming Language :: Python :: 3.7
Classifier: Environment :: Console
Requires-Python: >=3.6
License-File: LICENSE
Requires-Dist: ptlibs (>=0.0.6)
Requires-Dist: cloudscraper
